{
  "manifestVersion": "3.2",
  "admin": {
    "address": "0x03a42D96527109b596478118Eb4626c18342a1a7",
    "txHash": "0x977ac2dca3f37a453460600d7a76e731db39aeb5f0a97534443ed62bf430c83e"
  },
  "proxies": [
    {
      "address": "0x96F954009CfA2F42fD1761D427dc64041C49296d",
      "txHash": "0xd62dd70ca306287e681c4409cc158e85302aa8aed6a749ffe035f28f3ef755df",
      "kind": "transparent"
    }
  ],
  "impls": {
    "f6b17504871b41049117d1b8d68ee62c42c6e19b4b9d462e972990f56b75b1be": {
      "address": "0x7E39De4F1AE99019Db2e38c7f2EbD34DeEE85ab6",
      "txHash": "0xdc240c24cfe7d2a5e08e6fd7d513a54d555d57bf0f7a19ca22f7bf0491dff151",
      "layout": {
        "storage": [
          {
            "contract": "Initializable",
            "label": "_initialized",
            "type": "t_bool",
            "src": "..\\@openzeppelin\\contracts-upgradeable\\proxy\\utils\\Initializable.sol:21"
          },
          {
            "contract": "Initializable",
            "label": "_initializing",
            "type": "t_bool",
            "src": "..\\@openzeppelin\\contracts-upgradeable\\proxy\\utils\\Initializable.sol:26"
          },
          {
            "contract": "ContextUpgradeable",
            "label": "__gap",
            "type": "t_array(t_uint256)50_storage",
            "src": "..\\@openzeppelin\\contracts-upgradeable\\utils\\ContextUpgradeable.sol:30"
          },
          {
            "contract": "ERC20Upgradeable",
            "label": "_balances",
            "type": "t_mapping(t_address,t_uint256)",
            "src": "..\\@openzeppelin\\contracts-upgradeable\\token\\ERC20\\ERC20Upgradeable.sol:36"
          },
          {
            "contract": "ERC20Upgradeable",
            "label": "_allowances",
            "type": "t_mapping(t_address,t_mapping(t_address,t_uint256))",
            "src": "..\\@openzeppelin\\contracts-upgradeable\\token\\ERC20\\ERC20Upgradeable.sol:38"
          },
          {
            "contract": "ERC20Upgradeable",
            "label": "_totalSupply",
            "type": "t_uint256",
            "src": "..\\@openzeppelin\\contracts-upgradeable\\token\\ERC20\\ERC20Upgradeable.sol:40"
          },
          {
            "contract": "ERC20Upgradeable",
            "label": "_name",
            "type": "t_string_storage",
            "src": "..\\@openzeppelin\\contracts-upgradeable\\token\\ERC20\\ERC20Upgradeable.sol:42"
          },
          {
            "contract": "ERC20Upgradeable",
            "label": "_symbol",
            "type": "t_string_storage",
            "src": "..\\@openzeppelin\\contracts-upgradeable\\token\\ERC20\\ERC20Upgradeable.sol:43"
          },
          {
            "contract": "ERC20Upgradeable",
            "label": "__gap",
            "type": "t_array(t_uint256)45_storage",
            "src": "..\\@openzeppelin\\contracts-upgradeable\\token\\ERC20\\ERC20Upgradeable.sol:361"
          }
        ],
        "types": {
          "t_mapping(t_address,t_uint256)": {
            "label": "mapping(address => uint256)"
          },
          "t_address": {
            "label": "address"
          },
          "t_uint256": {
            "label": "uint256"
          },
          "t_mapping(t_address,t_mapping(t_address,t_uint256))": {
            "label": "mapping(address => mapping(address => uint256))"
          },
          "t_string_storage": {
            "label": "string"
          },
          "t_array(t_uint256)45_storage": {
            "label": "uint256[45]"
          },
          "t_array(t_uint256)50_storage": {
            "label": "uint256[50]"
          },
          "t_bool": {
            "label": "bool"
          }
        }
      }
    }
  }
}
